hanint/__init__.py
hanint/index.py
hanint-0.2.0.dist-info/METADATA
hanint-0.2.0.dist-info/WHEEL
hanint-0.2.0.dist-info/entry_points.txt
hanint-0.2.0.dist-info/top_level.txt
hanint-0.2.0.dist-info/RECORD
