Metadata-Version: 2.1
Name: hanint
Version: 0.2.0
Summary: 数字转汉字，如：`101`转`一百零一`
Home-page: https://github.com/ngolin/hanint
Author: 李鸿章
Author-email: paindo@163.com
License: UNKNOWN
Platform: UNKNOWN
Classifier: Programming Language :: Python :: 3
Classifier: License :: OSI Approved :: MIT License
Classifier: Operating System :: OS Independent
